omega/__init__.py
omega/cli/configuration.py
omega/cli/convert.py
omega/cli/main.py
omega/cli/spotter.py
snypr_cli-0.1.2.dist-info/entry_points.txt
snypr_cli-0.1.2.dist-info/WHEEL
snypr_cli-0.1.2.dist-info/METADATA
snypr_cli-0.1.2.dist-info/RECORD
