Metadata-Version: 2.1
Name: snypr-cli
Version: 0.1.2
Summary: A simple tool for converting Sigma detection rules to SNYPR Spotter queries.
Home-page: https://github.com/Securonix/SigmaToSnypr
Author: Securonix Threat Labs
Requires-Python: >=3.9,<4.0
Classifier: Programming Language :: Python :: 3
Classifier: Programming Language :: Python :: 3.10
Classifier: Programming Language :: Python :: 3.9
Requires-Dist: click (>=8.1.3,<9.0.0)
Requires-Dist: pysigma (>=0.6.5,<0.7.0)
Requires-Dist: sigmatools (>=0.21.0,<0.22.0)
Project-URL: Repository, https://github.com/Securonix/SigmaToSnypr
